LICENSE
README.md
setup.py
crypts/__init__.py
crypts/asymmetric.py
crypts/crypts.py
crypts/hybrid.py
crypts/simple.py
crypts/ultra.py
crypts.egg-info/PKG-INFO
crypts.egg-info/SOURCES.txt
crypts.egg-info/dependency_links.txt
crypts.egg-info/requires.txt
crypts.egg-info/top_level.txt